[
    {
        "City": "City1",
        "CompanyName": "SqzsSyVvSxjtLLjCSvENItiZNngqvRtA",
        "ContactName": "ContactName1",
        "Relationship": "jdWGqddNr"
    },
    {
        "City": "City2",
        "CompanyName": "UXkrHtrveDvoqPAWJbEvJignkzjxpnLR",
        "ContactName": "ContactName2",
        "Relationship": "TUeDWygdB"
    },
    {
        "City": "City3",
        "CompanyName": "TizagdPrZLMcpIfvYDodcsYyYgPiWVJV",
        "ContactName": "ContactName3",
        "Relationship": "cWAZDwAjj"
    },
    {
        "City": "City4",
        "CompanyName": "gmYcgninctuigTDFeztEqjuoZNmJnfxF",
        "ContactName": "ContactName4",
        "Relationship": "mvjiIcoCX"
    },
    {
        "City": "City5",
        "CompanyName": "VMKueutuHkWwmQVZfeIISPBHhzaQTMFY",
        "ContactName": "ContactName5",
        "Relationship": "vqrKysHXR"
    },
    {
        "City": "City6",
        "CompanyName": "JeuwHFQbTvWNqvlCRuxVBfacWXObohbx",
        "ContactName": "ContactName6",
        "Relationship": "CeEugvCDu"
    },
    {
        "City": "City7",
        "CompanyName": "oLMfpissrgGpKHUoWfeswcyGHrsEhsXB",
        "ContactName": "ContactName7",
        "Relationship": "yaaJnzvFa"
    },
    {
        "City": "City8",
        "CompanyName": "ZFUtKJZYjaIycgZGDhntQHggiXBQHULN",
        "ContactName": "ContactName8",
        "Relationship": "ItPMrTpLq"
    },
    {
        "City": "City9",
        "CompanyName": "qicGRCRfIuKkKGOspmmQufaYZutJSlCr",
        "ContactName": "ContactName9",
        "Relationship": "IYuRoUWvp"
    },
    {
        "City": "City10",
        "CompanyName": "AqrojBVHyWSNMttPQjsadlILfxtFklTJ",
        "ContactName": "ContactName10",
        "Relationship": "RsEUInAbx"
    },
    {
        "City": "City11",
        "CompanyName": "RbXcgjvcjSPTQuNlplycnBNbuPULTdgv",
        "ContactName": "ContactName11",
        "Relationship": "cWFMtBhsy"
    },
    {
        "City": "City12",
        "CompanyName": "omPOuNiwYtBnDRAdNnURclkANepVkFMq",
        "ContactName": "ContactName12",
        "Relationship": "FWjaBiteY"
    },
    {
        "City": "City13",
        "CompanyName": "kMkePVmjbqMZETmvlpHrxmMZLXAGZiyo",
        "ContactName": "ContactName13",
        "Relationship": "uKcVBZiQm"
    },
    {
        "City": "City14",
        "CompanyName": "vLGnciIUlBNbXXmuaNJbXcnYfcRTZruj",
        "ContactName": "ContactName14",
        "Relationship": "uoGCGqsYg"
    },
    {
        "City": "City15",
        "CompanyName": "slJkVqquokjBgoYgOquJbEFndSazndKJ",
        "ContactName": "ContactName15",
        "Relationship": "VrDsJqGRK"
    },
    {
        "City": "City16",
        "CompanyName": "ljvzRIShUfxCNixcdrKoCuhUuTfmEmXp",
        "ContactName": "ContactName16",
        "Relationship": "tVYHdfbjZ"
    },
    {
        "City": "City17",
        "CompanyName": "FACSsWzWPJrywLKARkltNelhkSKtQRDI",
        "ContactName": "ContactName17",
        "Relationship": "dtLxXSYNw"
    },
    {
        "City": "City18",
        "CompanyName": "zFbnuJRFBfGuSvzuNHJElCeEsujLfbCH",
        "ContactName": "ContactName18",
        "Relationship": "uIiXTWDUD"
    },
    {
        "City": "City19",
        "CompanyName": "cgWjLlnnmOMhjVIWGQeMRGfXrqBUBKvj",
        "ContactName": "ContactName19",
        "Relationship": "JwCJmkDCp"
    },
    {
        "City": "City20",
        "CompanyName": "YKuiRWsDTcfGfyeKsgseaStoCPKKCJOO",
        "ContactName": "ContactName20",
        "Relationship": "ylCLbuAja"
    },
    {
        "City": "City21",
        "CompanyName": "khDJdfLBLbjTFrThwBbroyjnuhlXYClh",
        "ContactName": "ContactName21",
        "Relationship": "DcmMMXcTb"
    },
    {
        "City": "City22",
        "CompanyName": "hkDpjSnjDlreyPmSYtSvTZxIPSpwXTqU",
        "ContactName": "ContactName22",
        "Relationship": "SSJDviCGc"
    },
    {
        "City": "City23",
        "CompanyName": "TyqssdUrNgJXGdxPoeoKxNwMqiXYIhgb",
        "ContactName": "ContactName23",
        "Relationship": "tovUjkqGX"
    },
    {
        "City": "City24",
        "CompanyName": "HJlzXMJggdnQJnlqUOEIkvgCvLurQShK",
        "ContactName": "ContactName24",
        "Relationship": "ZzzwYQrXz"
    },
    {
        "City": "City25",
        "CompanyName": "bhKtkSupRLxRYnEMIlfkgEGgxEpUpMLQ",
        "ContactName": "ContactName25",
        "Relationship": "JAvPaunub"
    },
    {
        "City": "City26",
        "CompanyName": "HUDKBNdKvbVIcwVmDLCKnXGSixXQAeqg",
        "ContactName": "ContactName26",
        "Relationship": "DXifRFcCL"
    },
    {
        "City": "City27",
        "CompanyName": "naqAlPUTiejospFgNQnhhtejZAVworBu",
        "ContactName": "ContactName27",
        "Relationship": "CqfhFynzb"
    },
    {
        "City": "City28",
        "CompanyName": "WNeojwcvmLftoPowsJhVIBjvlcWufSFb",
        "ContactName": "ContactName28",
        "Relationship": "urTrXIiJM"
    },
    {
        "City": "City29",
        "CompanyName": "UYPBsduCpsTPSmsiveCWbjkmSjlsbAPz",
        "ContactName": "ContactName29",
        "Relationship": "StdJbfyWT"
    },
    {
        "City": "City30",
        "CompanyName": "AFwBnMCNBeVmxcpaiYqbgUuvcgxruVgh",
        "ContactName": "ContactName30",
        "Relationship": "soeMgfRej"
    },
    {
        "City": "City31",
        "CompanyName": "CdJawXfzXrIZAITjJmCOsIMQjsgHbsTu",
        "ContactName": "ContactName31",
        "Relationship": "CfsOulTWA"
    },
    {
        "City": "City32",
        "CompanyName": "LcaZAlBhIQupRqLgZegmxOTOKOfPYrNJ",
        "ContactName": "ContactName32",
        "Relationship": "UuXzAWscK"
    },
    {
        "City": "City33",
        "CompanyName": "uuIlvYqTsCGWghFuxqwwJedYtHYUAeVT",
        "ContactName": "ContactName33",
        "Relationship": "nwPfrFaEv"
    },
    {
        "City": "City34",
        "CompanyName": "UEvgBDJvaoAamWhRJdHQYezCiENdthqU",
        "ContactName": "ContactName34",
        "Relationship": "mQlkhaEfi"
    },
    {
        "City": "City35",
        "CompanyName": "pgAaLxibkYIDjlvzazzqMFvIdGXVpNyC",
        "ContactName": "ContactName35",
        "Relationship": "dyzUfRTTS"
    },
    {
        "City": "City36",
        "CompanyName": "xcANRFOzHOYPQuWvnybMWUiBBWCVBcIa",
        "ContactName": "ContactName36",
        "Relationship": "uKNPvIyax"
    },
    {
        "City": "City37",
        "CompanyName": "NYvYKIOcvTKWtHVquUtuvAowlSyDLdRB",
        "ContactName": "ContactName37",
        "Relationship": "rrNfEWIpU"
    },
    {
        "City": "City38",
        "CompanyName": "TmYPpbhUZonUrVfjgljEEiszThumCYbL",
        "ContactName": "ContactName38",
        "Relationship": "pTCJUXtAf"
    },
    {
        "City": "City39",
        "CompanyName": "aQPkxekOIUSgEguOqHnEeESQAJRuaRxy",
        "ContactName": "ContactName39",
        "Relationship": "ZuKjaQUWq"
    },
    {
        "City": "City40",
        "CompanyName": "kdcRZuPKnMgSmwCPFMmrowhUhHrRBFjO",
        "ContactName": "ContactName40",
        "Relationship": "WiRhDVVJm"
    },
    {
        "City": "City41",
        "CompanyName": "vALzZPYIISMiAGoPnVdUSNDwUTbChVVf",
        "ContactName": "ContactName41",
        "Relationship": "UJtucQCPz"
    },
    {
        "City": "City42",
        "CompanyName": "JLTdTiMlMISLXBLdINGujPIlUhCrCtbQ",
        "ContactName": "ContactName42",
        "Relationship": "LGZUWTKCk"
    },
    {
        "City": "City43",
        "CompanyName": "mIwMuxJTTrxaMoBrWPnYJDQJhhLLPkiY",
        "ContactName": "ContactName43",
        "Relationship": "LOtMMskrE"
    },
    {
        "City": "City44",
        "CompanyName": "kEKuErsuUPmuQVFmDiTmrOknBLrcJMBV",
        "ContactName": "ContactName44",
        "Relationship": "UVtKdDJWv"
    },
    {
        "City": "City45",
        "CompanyName": "GczGyQkJoMyanvXmchBeMsKKahPaQKjj",
        "ContactName": "ContactName45",
        "Relationship": "QzhmdiwZj"
    },
    {
        "City": "City46",
        "CompanyName": "nyGoJMAmwsnOaAuUbUdefVrYBWoXxfOh",
        "ContactName": "ContactName46",
        "Relationship": "mmJSmroqu"
    },
    {
        "City": "City47",
        "CompanyName": "ElHgDZXfUqeuLwTDQifmQHPORJJvwyFW",
        "ContactName": "ContactName47",
        "Relationship": "gRkvdKQGP"
    },
    {
        "City": "City48",
        "CompanyName": "iiMppwefDXOVKoZUVNxoAChqsKxerodj",
        "ContactName": "ContactName48",
        "Relationship": "lAIbNCGbQ"
    },
    {
        "City": "City49",
        "CompanyName": "rsnCYVAvjSgLWuNlCcgRaoikAvEQhBeG",
        "ContactName": "ContactName49",
        "Relationship": "AeZAQalJS"
    },
    {
        "City": "City50",
        "CompanyName": "JuBCuLXisCfQsntkrqfhQrmwiLQiZZgz",
        "ContactName": "ContactName50",
        "Relationship": "CKBHkDnNK"
    },
    {
        "City": "City51",
        "CompanyName": "jRvHHUSZcueypokhDattlDfEFQXPanLk",
        "ContactName": "ContactName51",
        "Relationship": "YgxnbREdX"
    },
    {
        "City": "City52",
        "CompanyName": "MvIqwzAJFmEckvQKWyDylZeUNSvYpcpk",
        "ContactName": "ContactName52",
        "Relationship": "pVevmdqkR"
    },
    {
        "City": "City53",
        "CompanyName": "NiIZVykzrcnigWDjVVeZOtdugBnqVnDb",
        "ContactName": "ContactName53",
        "Relationship": "fVQeVPFtF"
    },
    {
        "City": "City54",
        "CompanyName": "PegSwWlTBbMpEnbpyJilNwXVROkzKtju",
        "ContactName": "ContactName54",
        "Relationship": "NAXEXhCUZ"
    },
    {
        "City": "City55",
        "CompanyName": "sxJWBVsoQDvTzQuqEhIysFInNBsvnHua",
        "ContactName": "ContactName55",
        "Relationship": "eAgLDFSov"
    },
    {
        "City": "City56",
        "CompanyName": "xDbncfmgbOnPcqbfevpCgVaEWdlRuhMF",
        "ContactName": "ContactName56",
        "Relationship": "vawkqDUOJ"
    },
    {
        "City": "City57",
        "CompanyName": "bEfWchmSwLGMNcQgRAjTtpMOZeYfIKlz",
        "ContactName": "ContactName57",
        "Relationship": "kxhSPvlPG"
    },
    {
        "City": "City58",
        "CompanyName": "BhUpXzdkyoRyylBlVPbIVmEheGCrDzZa",
        "ContactName": "ContactName58",
        "Relationship": "IDiukMASc"
    },
    {
        "City": "City59",
        "CompanyName": "PPkZJetbbjAuEZuMcskkQQOaQHJgtoFL",
        "ContactName": "ContactName59",
        "Relationship": "uZzxYmvKM"
    },
    {
        "City": "City60",
        "CompanyName": "ztHRAnmBSKmqFkMXNmYQsXxjqfqidgKe",
        "ContactName": "ContactName60",
        "Relationship": "hvLaqinDV"
    },
    {
        "City": "City61",
        "CompanyName": "HtGVmjEoKKfejDajsHXFvxeNUfEXcOCb",
        "ContactName": "ContactName61",
        "Relationship": "SuOQciiAe"
    },
    {
        "City": "City62",
        "CompanyName": "IeXYoxsBEeRxPBXjqLhFgqMcuaTOJHBS",
        "ContactName": "ContactName62",
        "Relationship": "TWQbxMOpR"
    },
    {
        "City": "City63",
        "CompanyName": "kZlTqsGJsiMNOJBZowvnHfKYcjjsPpit",
        "ContactName": "ContactName63",
        "Relationship": "AeotaoiGm"
    },
    {
        "City": "City64",
        "CompanyName": "akxagakMovuXSfOLuVodFPWyUoaBquLQ",
        "ContactName": "ContactName64",
        "Relationship": "XQuFjIWRv"
    },
    {
        "City": "City65",
        "CompanyName": "eYErTWevFxmfLnstUeHZqPQuQydVAdqt",
        "ContactName": "ContactName65",
        "Relationship": "NmWXujZHz"
    },
    {
        "City": "City66",
        "CompanyName": "DhCyecJNMyYiGIqnQIYUegcapOMYFrrd",
        "ContactName": "ContactName66",
        "Relationship": "qwPbpPdds"
    },
    {
        "City": "City67",
        "CompanyName": "MOfMOaeWOrcasDzrAHTpgVnFMCZzezXh",
        "ContactName": "ContactName67",
        "Relationship": "ISTHgbqwz"
    },
    {
        "City": "City68",
        "CompanyName": "XXGJsgtBQcvLjOqyJSNEayhskuuzTZDB",
        "ContactName": "ContactName68",
        "Relationship": "BlCYebHrS"
    },
    {
        "City": "City69",
        "CompanyName": "WsbwyYGzmohITMciHqqDoMtirWYRvJqk",
        "ContactName": "ContactName69",
        "Relationship": "FvCWAzFKJ"
    },
    {
        "City": "City70",
        "CompanyName": "RSTGuRJMENLHApiJvWinFRJtiPYbscui",
        "ContactName": "ContactName70",
        "Relationship": "OdvFWXOLn"
    },
    {
        "City": "City71",
        "CompanyName": "hDJSJwbZByyrGDpwTkHhzoWhCPoKefOZ",
        "ContactName": "ContactName71",
        "Relationship": "rZazcHzGV"
    },
    {
        "City": "City72",
        "CompanyName": "rqMkQKUbhKoCZdOfHlkuwaTGwlSTtPIA",
        "ContactName": "ContactName72",
        "Relationship": "uAGqMnBfX"
    },
    {
        "City": "City73",
        "CompanyName": "yWfAqxviGgcMzbSQkFOpPOkawXiIaMAN",
        "ContactName": "ContactName73",
        "Relationship": "KUyavGmJs"
    },
    {
        "City": "City74",
        "CompanyName": "BtGPyNMhmqIVjbPaLypRUOUUjlYmBbie",
        "ContactName": "ContactName74",
        "Relationship": "hygdNvAIz"
    },
    {
        "City": "City75",
        "CompanyName": "rOQiGRamadvAFwaLlXcmkeKjLWmoYIYc",
        "ContactName": "ContactName75",
        "Relationship": "QPBhVfKME"
    },
    {
        "City": "City76",
        "CompanyName": "MqzPxSbPcFDyOVLcBIKJENEgfusWAijn",
        "ContactName": "ContactName76",
        "Relationship": "BFmKpoYQh"
    },
    {
        "City": "City77",
        "CompanyName": "qhLtQWoxrwnZVcvNtuGFTJUpjwsrTDtG",
        "ContactName": "ContactName77",
        "Relationship": "hZGoGhBRZ"
    },
    {
        "City": "City78",
        "CompanyName": "SBhrJVYAtGDtKarWulCRSLUYiucXMzpQ",
        "ContactName": "ContactName78",
        "Relationship": "fIuhpEdZy"
    },
    {
        "City": "City79",
        "CompanyName": "RCwnylPONzaEKdkfPGSiKALzOJqSEDEJ",
        "ContactName": "ContactName79",
        "Relationship": "kRoEPgMaq"
    },
    {
        "City": "City80",
        "CompanyName": "koAfwHQvweVfSzsumfnmrHHxFDEfzfUa",
        "ContactName": "ContactName80",
        "Relationship": "EnQHYnSPP"
    },
    {
        "City": "City81",
        "CompanyName": "MkNoTWvGIyWcEiLAdBmcovQxGUBdYqxg",
        "ContactName": "ContactName81",
        "Relationship": "kokGqnZBv"
    },
    {
        "City": "City82",
        "CompanyName": "gHOnFzxwiwxqUHgoeHsJaVAxcHaMdVRE",
        "ContactName": "ContactName82",
        "Relationship": "aWHaWUhUU"
    },
    {
        "City": "City83",
        "CompanyName": "HavZJjFAlZQEcWpgWssmqIlEXyWkCoIW",
        "ContactName": "ContactName83",
        "Relationship": "bEZgboLNi"
    },
    {
        "City": "City84",
        "CompanyName": "aZiqjwELXPNBdKBxbzVnbkWqoHGlZgRM",
        "ContactName": "ContactName84",
        "Relationship": "nmkeQIcGl"
    },
    {
        "City": "City85",
        "CompanyName": "RUaXfUaydeMRfpsFTkzQLpXeaUIMXqac",
        "ContactName": "ContactName85",
        "Relationship": "zgiqkAMSP"
    },
    {
        "City": "City86",
        "CompanyName": "BcSwycmSgZboKyvJQEPJDFEvLcEnAAgu",
        "ContactName": "ContactName86",
        "Relationship": "lJKVgNgdV"
    },
    {
        "City": "City87",
        "CompanyName": "TsjWPctYmWQgJVhyNDYFbwpSFqkLanxZ",
        "ContactName": "ContactName87",
        "Relationship": "lJQmDVvFW"
    },
    {
        "City": "City88",
        "CompanyName": "efTJQVyUDeESFjylggpizoiFhuOEvftr",
        "ContactName": "ContactName88",
        "Relationship": "ASSxyqdlG"
    },
    {
        "City": "City89",
        "CompanyName": "PQVUiPibmjxmPRBYZQgDPrhADyLAyZfd",
        "ContactName": "ContactName89",
        "Relationship": "HfxVhSIFJ"
    },
    {
        "City": "City90",
        "CompanyName": "YrVeBfxgJwtksfeXTAYQhLoIOHxeOnQs",
        "ContactName": "ContactName90",
        "Relationship": "acaOGPVsz"
    },
    {
        "City": "City91",
        "CompanyName": "NFBQsnscJnMbGjwuQFtyHUiaZJgVmrId",
        "ContactName": "ContactName91",
        "Relationship": "RBukRCSaU"
    },
    {
        "City": "City92",
        "CompanyName": "GtiixxJtCqHmVgczjgeegxwrbyhdSfeS",
        "ContactName": "ContactName92",
        "Relationship": "XKFrLDGJr"
    },
    {
        "City": "City93",
        "CompanyName": "SAQtVgarnHFonAnmTFMHJFCUGncsZlXE",
        "ContactName": "ContactName93",
        "Relationship": "CAzKDiCar"
    },
    {
        "City": "City94",
        "CompanyName": "ryvKhQiLhzXmJKShaddmukQpDpXTWvXS",
        "ContactName": "ContactName94",
        "Relationship": "ndJWIcKUE"
    },
    {
        "City": "City95",
        "CompanyName": "SHRMRtfBVTaeXeaedxZmokeIfngTzyEc",
        "ContactName": "ContactName95",
        "Relationship": "CnSLwOosq"
    },
    {
        "City": "City96",
        "CompanyName": "BqomCtUEAQdPAAMSKudwtbrTaPEkRRiT",
        "ContactName": "ContactName96",
        "Relationship": "QqgOaAaJv"
    },
    {
        "City": "City97",
        "CompanyName": "UzUwNNmcrkjEKjqzlSGdpGwictMDtgij",
        "ContactName": "ContactName97",
        "Relationship": "JpkJgqaZO"
    },
    {
        "City": "City98",
        "CompanyName": "MQcflqFYToadIvxaQkaAJJvFuTCuRmzV",
        "ContactName": "ContactName98",
        "Relationship": "aCLtrKmRn"
    },
    {
        "City": "City99",
        "CompanyName": "MrnrQMyZDKyskoLWTyvuDiiHBEIzmXCW",
        "ContactName": "ContactName99",
        "Relationship": "FPNdhiVXo"
    },
    {
        "City": "City100",
        "CompanyName": "FpDWdtPMdpXmHFvQZxoDgWIfqldtpJHe",
        "ContactName": "ContactName100",
        "Relationship": "kMrliLJlN"
    },
    {
        "City": "City101",
        "CompanyName": "IgLZvUrLtPYIseITRrZQBCnuaRVcPPTz",
        "ContactName": "ContactName101",
        "Relationship": "dEelDRxjt"
    },
    {
        "City": "City102",
        "CompanyName": "PVWVSJEovSRRKeLAXYxksXYIkGgxCVUy",
        "ContactName": "ContactName102",
        "Relationship": "IIOGDnrsc"
    },
    {
        "City": "City103",
        "CompanyName": "qrvyaLbsHbAJDtTPIxCxlczUZKzQTKxm",
        "ContactName": "ContactName103",
        "Relationship": "nLUvLhojY"
    },
    {
        "City": "City104",
        "CompanyName": "ydlahqlSxdjIDunSzacUXcnFaItgwIMA",
        "ContactName": "ContactName104",
        "Relationship": "tZjxbLIdf"
    },
    {
        "City": "City105",
        "CompanyName": "jXCbgThcooZPLIRFGRVdfSdhhCDPqFUd",
        "ContactName": "ContactName105",
        "Relationship": "tGlWlXEFC"
    },
    {
        "City": "City106",
        "CompanyName": "jfCGWlrqImIeDHeGBKZHIGRyNwelRHGq",
        "ContactName": "ContactName106",
        "Relationship": "PyqMrwAMC"
    },
    {
        "City": "City107",
        "CompanyName": "DTwtrJvThSlPNHxTaoCcEpaDzXqaOHYA",
        "ContactName": "ContactName107",
        "Relationship": "EaqEzUhGi"
    },
    {
        "City": "City108",
        "CompanyName": "scsPjcaaZOohmTOAMGKYduQcAvPqeiEC",
        "ContactName": "ContactName108",
        "Relationship": "XTvLHRPPa"
    },
    {
        "City": "City109",
        "CompanyName": "hmKdlaYcmNoOdJUqDFifSuYLUrAOUawv",
        "ContactName": "ContactName109",
        "Relationship": "EhEWucVRm"
    },
    {
        "City": "City110",
        "CompanyName": "KvFdpMZgTrsFhuvyzjbyFObWOnjantrX",
        "ContactName": "ContactName110",
        "Relationship": "jvMOuwqzQ"
    },
    {
        "City": "City111",
        "CompanyName": "RAfUIolOTdUBDEqGRHysNwUYWIIiEsOs",
        "ContactName": "ContactName111",
        "Relationship": "lUpUxhREI"
    },
    {
        "City": "City112",
        "CompanyName": "vcPfvuSFXXVkhEzAtCySvrIIGuVetaNu",
        "ContactName": "ContactName112",
        "Relationship": "nUOrEOBch"
    },
    {
        "City": "City113",
        "CompanyName": "fssKTNwDqGFmHWeWbQNXugvkyEPqYiMl",
        "ContactName": "ContactName113",
        "Relationship": "eqFLrIjjX"
    },
    {
        "City": "City114",
        "CompanyName": "nnSJEqOSrEQHMiCXQEBnRTAFyCTsjRYY",
        "ContactName": "ContactName114",
        "Relationship": "KBCWiARzh"
    },
    {
        "City": "City115",
        "CompanyName": "dTpxqbOovnFfrbboEFdYEbPAgXHBDbHv",
        "ContactName": "ContactName115",
        "Relationship": "CMnUzUDry"
    },
    {
        "City": "City116",
        "CompanyName": "vnwcInYLgglovhakERfgqhzUxOSPIstY",
        "ContactName": "ContactName116",
        "Relationship": "qVTtRqEcw"
    },
    {
        "City": "City117",
        "CompanyName": "eBFQnEZrmiIrgXsUyCVjYQWgEFNsbJTF",
        "ContactName": "ContactName117",
        "Relationship": "FTswRZzat"
    },
    {
        "City": "City118",
        "CompanyName": "sHYAGhbCXlZkcWjdesLCGbfkxiCVwYIo",
        "ContactName": "ContactName118",
        "Relationship": "wUzkrqeJl"
    },
    {
        "City": "City119",
        "CompanyName": "NVUDSeHuwkarWKlhjHxzDgRqviZQBGtd",
        "ContactName": "ContactName119",
        "Relationship": "gxRqWLMTE"
    },
    {
        "City": "City120",
        "CompanyName": "YEHnfiklnBQwpGTRFPXXoOqznZoSvdco",
        "ContactName": "ContactName120",
        "Relationship": "PoGeLwyya"
    },
    {
        "City": "City121",
        "CompanyName": "DXFlQPaNwzumrPtZESYObBHFhxlcsRbz",
        "ContactName": "ContactName121",
        "Relationship": "absTGGrZf"
    },
    {
        "City": "City122",
        "CompanyName": "xFWzSbLajRzykGAJJujDRYxnszLkxEKH",
        "ContactName": "ContactName122",
        "Relationship": "jutumRnDR"
    },
    {
        "City": "City123",
        "CompanyName": "XjwMMVNpKcqYqsVPQQTBxtomLmPAYAgK",
        "ContactName": "ContactName123",
        "Relationship": "XFDHnMXeF"
    },
    {
        "City": "City124",
        "CompanyName": "VisAziJuHuxDVFEExcmuwqztTeHWRPXs",
        "ContactName": "ContactName124",
        "Relationship": "KGltYXxJS"
    },
    {
        "City": "City125",
        "CompanyName": "sJXEdUYTdGyPAoXanREfaCLZULbuawMu",
        "ContactName": "ContactName125",
        "Relationship": "djtSklhZR"
    },
    {
        "City": "City126",
        "CompanyName": "VgjkxaRYysmVknLDbJhmkPJaAvtBFjmA",
        "ContactName": "ContactName126",
        "Relationship": "ViToWxPvF"
    },
    {
        "City": "City127",
        "CompanyName": "RNRuVCWMJktYtoXBCBlGfJxQySUxwXwx",
        "ContactName": "ContactName127",
        "Relationship": "aLDWZjODs"
    },
    {
        "City": "City128",
        "CompanyName": "xhWMCHAeBDklvTwGGbYqdkDmOLqBXmPc",
        "ContactName": "ContactName128",
        "Relationship": "lcBsUINna"
    },
    {
        "City": "City129",
        "CompanyName": "xxtMBNOqfMPVHWvjjpHQahqTnEOmeUCG",
        "ContactName": "ContactName129",
        "Relationship": "eCqTSzjTn"
    },
    {
        "City": "City130",
        "CompanyName": "EalobAAHmdGDeymVRVanGWUBwyXOvYoP",
        "ContactName": "ContactName130",
        "Relationship": "jWANLQZvm"
    },
    {
        "City": "City131",
        "CompanyName": "KHiJmoBxXgyxrBCuSDOmWqRhPPQjoiZt",
        "ContactName": "ContactName131",
        "Relationship": "ByfWfyEvi"
    },
    {
        "City": "City132",
        "CompanyName": "cjtxshEfLKYpBFiwVcLHRZAiGzOpyaqB",
        "ContactName": "ContactName132",
        "Relationship": "DJQFEPqLx"
    },
    {
        "City": "City133",
        "CompanyName": "LsrjAXmbEVDGIIfjTbiNEeFxdAbBdUij",
        "ContactName": "ContactName133",
        "Relationship": "RdkhOYSyy"
    },
    {
        "City": "City134",
        "CompanyName": "zkmKTwfGkDCXTdqdOBocCrZcLUdVwCGN",
        "ContactName": "ContactName134",
        "Relationship": "yVDeqjgGt"
    },
    {
        "City": "City135",
        "CompanyName": "MNPqFrXnGKXNvmtZYfUqLySxzqKeMhfK",
        "ContactName": "ContactName135",
        "Relationship": "MBziFtDqO"
    },
    {
        "City": "City136",
        "CompanyName": "ZwpLeauBNrLaVtCACQxBrgnPnZFfXdYj",
        "ContactName": "ContactName136",
        "Relationship": "zQjtCMhXB"
    },
    {
        "City": "City137",
        "CompanyName": "wYPBRqNqgxAciXERRPCNIwMPRdeTxkJM",
        "ContactName": "ContactName137",
        "Relationship": "FFQRuMeNm"
    },
    {
        "City": "City138",
        "CompanyName": "ijhxYiqzQgdQWFOHLUysHKiyzMrhJgqE",
        "ContactName": "ContactName138",
        "Relationship": "jqBEnxWfM"
    },
    {
        "City": "City139",
        "CompanyName": "ChYAqCOLokYnbRNhobkvTCoPnUujUOBB",
        "ContactName": "ContactName139",
        "Relationship": "zdGlaPxMh"
    },
    {
        "City": "City140",
        "CompanyName": "qLjwrZCXKVRGZerhwOYIbiTiFpojjdrP",
        "ContactName": "ContactName140",
        "Relationship": "ABbkWVRul"
    },
    {
        "City": "City141",
        "CompanyName": "YqNIgqoImOjLqUWOxxTlOZKxpQZLowAj",
        "ContactName": "ContactName141",
        "Relationship": "cwOrqnEih"
    },
    {
        "City": "City142",
        "CompanyName": "pyXKaSaifqYvNjMUmIQGkWvVXKSxBCYh",
        "ContactName": "ContactName142",
        "Relationship": "dmOAHBWYL"
    },
    {
        "City": "City143",
        "CompanyName": "GRoDLdLzWqxCBCVhFuGKEapbmGbdCAPw",
        "ContactName": "ContactName143",
        "Relationship": "pwZoUmMwF"
    },
    {
        "City": "City144",
        "CompanyName": "JsGUuhfuGlwEUpiYuVPgpVdIBjzOMifU",
        "ContactName": "ContactName144",
        "Relationship": "TlwEVNDMh"
    },
    {
        "City": "City145",
        "CompanyName": "XJTEiWpOOjVPMUZvFvbmHyAsCfXjLczd",
        "ContactName": "ContactName145",
        "Relationship": "hIMIiomvG"
    },
    {
        "City": "City146",
        "CompanyName": "YNgMDlTxbGPEbzugHRBKknXkHIldhOpf",
        "ContactName": "ContactName146",
        "Relationship": "NxZCaVoGq"
    },
    {
        "City": "City147",
        "CompanyName": "TEPuWYAunXNnKyYTRYmVXtdUJOkrRlLP",
        "ContactName": "ContactName147",
        "Relationship": "iefpmlMdI"
    },
    {
        "City": "City148",
        "CompanyName": "MguPrBCcAcVapCiEYMrSatUmjooWvwEl",
        "ContactName": "ContactName148",
        "Relationship": "EFpQPDthq"
    },
    {
        "City": "City149",
        "CompanyName": "alzYxfQMmQOEziTGhKLWiRppEfcmCPdT",
        "ContactName": "ContactName149",
        "Relationship": "XRpUzXDSk"
    },
    {
        "City": "City150",
        "CompanyName": "dLuBwXEDegvecaZXBTsqKnjKkhCIZJPe",
        "ContactName": "ContactName150",
        "Relationship": "NqjIBgfkc"
    },
    {
        "City": "City151",
        "CompanyName": "oCZfMYvocmealDovDIznwpxjauSUQDen",
        "ContactName": "ContactName151",
        "Relationship": "lGrcDOWYJ"
    },
    {
        "City": "City152",
        "CompanyName": "RFHMMEnMrLkYNfVDbMpjhxwFWUfXgADr",
        "ContactName": "ContactName152",
        "Relationship": "qjhnAvtFg"
    },
    {
        "City": "City153",
        "CompanyName": "OhzgFndJVBlNhYowhYjkPsXNUkQgPNMX",
        "ContactName": "ContactName153",
        "Relationship": "tzbLUubgt"
    },
    {
        "City": "City154",
        "CompanyName": "SscSprlZNajPNLQBxdlmXLzBnpipqmQR",
        "ContactName": "ContactName154",
        "Relationship": "vLkSgqEgO"
    },
    {
        "City": "City155",
        "CompanyName": "bHKRldzybePbmnfUEPuNQBAMLUWmsMkR",
        "ContactName": "ContactName155",
        "Relationship": "fGyrQINFX"
    },
    {
        "City": "City156",
        "CompanyName": "utwUbSxLIfffnKjPjPDptEQnjbBEhJQL",
        "ContactName": "ContactName156",
        "Relationship": "TxfPvQNqY"
    },
    {
        "City": "City157",
        "CompanyName": "mhcfycgYGowQGPKtvQUJAqydqLmYgjRu",
        "ContactName": "ContactName157",
        "Relationship": "UQfRebhmp"
    },
    {
        "City": "City158",
        "CompanyName": "SoFMEHBHecSnfayNXtNozjntZtEmlNZS",
        "ContactName": "ContactName158",
        "Relationship": "wydcAYtrc"
    },
    {
        "City": "City159",
        "CompanyName": "JmqowpYkhatplUnVgZXuGiqHcqQqwUDA",
        "ContactName": "ContactName159",
        "Relationship": "xJbRnRPRW"
    },
    {
        "City": "City160",
        "CompanyName": "SjaArsNwYMdlgPlndyoxOKEADGluCuxF",
        "ContactName": "ContactName160",
        "Relationship": "ftjuyfHVe"
    }
]